iomete_airflow_plugin/__init__.py
iomete_airflow_plugin/hook.py
iomete_airflow_plugin/iomete_operator.py
iomete_airflow_plugin/plugin.py
iomete_airflow_plugin-1.0.2.dist-info/METADATA
iomete_airflow_plugin-1.0.2.dist-info/WHEEL
iomete_airflow_plugin-1.0.2.dist-info/entry_points.txt
iomete_airflow_plugin-1.0.2.dist-info/top_level.txt
iomete_airflow_plugin-1.0.2.dist-info/RECORD
