Metadata-Version: 2.1
Name: iomete-airflow-plugin
Version: 1.0.2
Summary: An Airflow plugin for interacting with IOMETE platform.
Home-page: https://github.com/iomete/iomete-airflow-plugin
Author: IOMETE
Author-email: support@iomete.com
License: Apache Software License 2.0
Keywords: iomete,airflow,airflow plugin
Classifier: Programming Language :: Python :: 3
Requires-Python: >=3.7
Requires-Dist: requests
Requires-Dist: setuptools ~=67.0.0
Requires-Dist: Flask ~=2.2.3
Requires-Dist: iomete-sdk ==2.0.0
Provides-Extra: dev
Requires-Dist: black ==19.10b0 ; extra == 'dev'
Requires-Dist: watchdog ==0.9.0 ; extra == 'dev'
Requires-Dist: twine ==1.14.0 ; extra == 'dev'
Requires-Dist: apache-airflow ~=2.5.1 ; extra == 'dev'
